registryspy/__init__.py
registryspy/data_viewer.py
registryspy/find_dialog.py
registryspy/helpers.py
registryspy/hive_info_table.py
registryspy/key_tree.py
registryspy/license_dialog.py
registryspy/registryspy.py
registryspy/third_party_licenses.txt
registryspy/value_table.py
registryspy/img/close.png
registryspy/img/close_all.png
registryspy/img/find.png
registryspy/img/find_next.png
registryspy/img/find_previous.png
registryspy/img/folder.png
registryspy/img/icon.ico
registryspy/img/icon.png
registryspy/img/open.png
registryspy/img/reg_bin.png
registryspy/img/reg_num.png
registryspy/img/reg_str.png
registryspy/img/splash.png
registryspy/img/wordmark.png
registryspy-1.1.0.dist-info/LICENSE
registryspy-1.1.0.dist-info/METADATA
registryspy-1.1.0.dist-info/WHEEL
registryspy-1.1.0.dist-info/entry_points.txt
registryspy-1.1.0.dist-info/top_level.txt
registryspy-1.1.0.dist-info/RECORD
