Metadata-Version: 2.1
Name: registryspy
Version: 1.1.0
Summary: Cross-platform Windows Registry browser
Home-page: https://github.com/andyjsmith/Registry-Spy
Author: Andy Smith
Keywords: registry,forensics,windows forensics,forensics tools
Classifier: Programming Language :: Python :: 3
Classifier: Programming Language :: Python :: 3.8
Classifier: Programming Language :: Python :: 3.9
Classifier: Programming Language :: Python :: 3.10
Classifier: Programming Language :: Python :: 3.11
Classifier: License :: OSI Approved :: GNU General Public License v3 (GPLv3)
Classifier: Operating System :: OS Independent
Classifier: Environment :: Win32 (MS Windows)
Classifier: Environment :: X11 Applications
Classifier: Environment :: X11 Applications :: Qt
Classifier: Environment :: MacOS X
Requires-Python: >=3.8
License-File: LICENSE
Requires-Dist: PySide6 (>=6.5)
Requires-Dist: python-registry (>=1.3.1)
